{
  "_links": {
    "self": {
      "href": "<base>/api/ontologies/duo/properties/http%253A%252F%252Fpurl.obolibrary.org%252Fobo%252FIAO_0000604?lang=en"
    }
  },
  "annotation": {
    "editor note": [
      "In OWL 2 add AnnotationPropertyRange xsd:dateTimeStamp"
    ],
    "editor preferred term": [
      "retired from use as of"
    ],
    "term editor": [
      "Alan Ruttenberg"
    ]
  },
  "description": [
    "relates a class of CRID to the date after which further instances should not be made, according to the central authority"
  ],
  "has_children": false,
  "iri": "http://purl.obolibrary.org/obo/IAO_0000604",
  "is_defining_ontology": false,
  "is_obsolete": false,
  "is_root": true,
  "label": "retired from use as of",
  "lang": "en",
  "obo_id": "IAO:0000604",
  "ontology_iri": "http://purl.obolibrary.org/obo/duo.owl",
  "ontology_name": "duo",
  "ontology_prefix": "DUO",
  "short_form": "IAO_0000604",
  "synonyms": []
}