{
  "appearsIn": [
    "partof"
  ],
  "curie": "PRIDE:0000675",
  "hasDirectChildren": false,
  "hasDirectParents": false,
  "hasHierarchicalChildren": false,
  "hasHierarchicalParents": true,
  "hierarchicalAncestor": [
    "http://purl.obolibrary.org/obo/PRIDE_0000674"
  ],
  "hierarchicalParent": [
    {
      "axioms": [
        {
          "childRelationToParent": "http://purl.obolibrary.org/obo/pride#part_of"
        }
      ],
      "type": [
        "reification"
      ],
      "value": "http://purl.obolibrary.org/obo/PRIDE_0000674"
    }
  ],
  "hierarchicalProperty": "http://www.w3.org/2000/01/rdf-schema#subClassOf",
  "http://www.w3.org/1999/02/22-rdf-syntax-ns#type": "http://www.w3.org/2002/07/owl#Class",
  "http://www.w3.org/2000/01/rdf-schema#label": "sample name",
  "http://www.w3.org/2000/01/rdf-schema#subClassOf": [
    "http://purl.obolibrary.org/obo/NCIT_C25507",
    {
      "http://www.w3.org/1999/02/22-rdf-syntax-ns#type": "http://www.w3.org/2002/07/owl#Restriction",
      "http://www.w3.org/2002/07/owl#onProperty": "http://purl.obolibrary.org/obo/pride#part_of",
      "http://www.w3.org/2002/07/owl#someValuesFrom": "http://purl.obolibrary.org/obo/PRIDE_0000674",
      "isObsolete": false
    }
  ],
  "imported": false,
  "iri": "http://purl.obolibrary.org/obo/PRIDE_0000675",
  "isDefiningOntology": false,
  "isObsolete": false,
  "isPreferredRoot": false,
  "label": [
    "sample name"
  ],
  "linkedEntities": {
    "http://purl.obolibrary.org/obo/NCIT_C25507": {
      "curie": "ncit:C25507",
      "source": "https://raw.githubusercontent.com/biopragmatics/bioregistry/main/exports/registry/registry.json",
      "url": "http://purl.obolibrary.org/obo/NCIT_C25507"
    },
    "http://purl.obolibrary.org/obo/PRIDE_0000674": {
      "curie": "PRIDE:0000674",
      "hasLocalDefinition": true,
      "label": [
        "human gut"
      ],
      "numAppearsIn": 1.0,
      "type": [
        "class",
        "entity"
      ]
    },
    "http://www.w3.org/2000/01/rdf-schema#label": {
      "curie": "RDFS:label",
      "definedBy": [
        "rdfs"
      ],
      "hasLocalDefinition": false,
      "label": [
        "label"
      ],
      "numAppearsIn": 4.0,
      "type": [
        "entity",
        "property"
      ]
    },
    "http://www.w3.org/2000/01/rdf-schema#subClassOf": {
      "curie": "RDFS:subClassOf",
      "definedBy": [
        "rdfs"
      ],
      "hasLocalDefinition": false,
      "label": [
        "subClassOf"
      ],
      "numAppearsIn": 2.0,
      "type": [
        "entity",
        "property"
      ]
    }
  },
  "linksTo": [
    "http://purl.obolibrary.org/obo/PRIDE_0000674",
    "http://www.w3.org/2000/01/rdf-schema#label",
    "http://www.w3.org/2000/01/rdf-schema#subClassOf"
  ],
  "numDescendants": 0.0,
  "numHierarchicalDescendants": 0.0,
  "ontologyId": "partof",
  "ontologyIri": "http://www.ebi.ac.uk/testcases/hierarchical-properties/partof.owl",
  "ontologyPreferredPrefix": "partof",
  "relatedTo": [
    {
      "http://www.w3.org/1999/02/22-rdf-syntax-ns#type": "http://www.w3.org/2002/07/owl#Restriction",
      "http://www.w3.org/2002/07/owl#onProperty": "http://purl.obolibrary.org/obo/pride#part_of",
      "http://www.w3.org/2002/07/owl#someValuesFrom": "http://purl.obolibrary.org/obo/PRIDE_0000674",
      "isObsolete": false,
      "property": "http://purl.obolibrary.org/obo/pride#part_of",
      "type": [
        "related"
      ],
      "value": "http://purl.obolibrary.org/obo/PRIDE_0000674"
    }
  ],
  "searchableAnnotationValues": false,
  "shortForm": "PRIDE_0000675",
  "type": [
    "class",
    "entity"
  ]
}