{
  "_links": {
    "ancestors": {
      "href": "<base>/api/ontologies/owl/terms/http%253A%252F%252Fwww.w3.org%252F2002%252F07%252Fowl%2523Ontology/ancestors"
    },
    "graph": {
      "href": "<base>/api/ontologies/owl/terms/http%253A%252F%252Fwww.w3.org%252F2002%252F07%252Fowl%2523Ontology/graph"
    },
    "hierarchicalAncestors": {
      "href": "<base>/api/ontologies/owl/terms/http%253A%252F%252Fwww.w3.org%252F2002%252F07%252Fowl%2523Ontology/hierarchicalAncestors"
    },
    "hierarchicalParents": {
      "href": "<base>/api/ontologies/owl/terms/http%253A%252F%252Fwww.w3.org%252F2002%252F07%252Fowl%2523Ontology/hierarchicalParents"
    },
    "jstree": {
      "href": "<base>/api/ontologies/owl/terms/http%253A%252F%252Fwww.w3.org%252F2002%252F07%252Fowl%2523Ontology/jstree"
    },
    "parents": {
      "href": "<base>/api/ontologies/owl/terms/http%253A%252F%252Fwww.w3.org%252F2002%252F07%252Fowl%2523Ontology/parents"
    },
    "self": {
      "href": "<base>/api/ontologies/owl/terms/http%253A%252F%252Fwww.w3.org%252F2002%252F07%252Fowl%2523Ontology?lang=en"
    }
  },
  "annotation": {},
  "description": [
    "The class of ontologies."
  ],
  "has_children": false,
  "iri": "http://www.w3.org/2002/07/owl#Ontology",
  "is_defining_ontology": true,
  "is_obsolete": false,
  "is_preferred_root": false,
  "is_root": false,
  "label": "Ontology",
  "lang": "en",
  "obo_id": "OWL:Ontology",
  "ontology_iri": "http://www.w3.org/2002/07/owl",
  "ontology_name": "owl",
  "short_form": "OWL_Ontology",
  "synonyms": []
}