{
  "appearsIn": [
    "owl2primer-object-property-domain-range-restriction"
  ],
  "curie": "Person",
  "hasDirectChildren": true,
  "hasDirectParents": false,
  "hasHierarchicalChildren": true,
  "hasHierarchicalParents": false,
  "http://www.w3.org/1999/02/22-rdf-syntax-ns#type": "http://www.w3.org/2002/07/owl#Class",
  "imported": false,
  "iri": "http://www.ebi.ac.uk/testcases/owl2primer/object-property-domain-range-restriction#Person",
  "isDefiningOntology": false,
  "isObsolete": false,
  "isPreferredRoot": false,
  "label": [
    "Person"
  ],
  "linkedEntities": {},
  "numDescendants": 2.0,
  "numHierarchicalDescendants": 2.0,
  "ontologyId": "owl2primer-object-property-domain-range-restriction",
  "ontologyIri": "http://www.ebi.ac.uk/testcases/owl2primer/object-property-domain-range-restriction.owl",
  "ontologyPreferredPrefix": "owl2primer-object-property-domain-range-restriction",
  "searchableAnnotationValues": false,
  "shortForm": "Person",
  "type": [
    "class",
    "entity"
  ]
}